{
	"inputs" : 
	[
		{
			"path" : "CMakeLists.txt"
		},
		{
			"isGenerated" : true,
			"path" : "build/CMakeFiles/3.26.2/CMakeSystem.cmake"
		},
		{
			"isCMake" : true,
			"isExternal" : true,
			"path" : "/usr/local/share/cmake-3.26/Modules/CMakeSystemSpecificInitialize.cmake"
		},
		{
			"isGenerated" : true,
			"path" : "build/CMakeFiles/3.26.2/CMakeCCompiler.cmake"
		},
		{
			"isGenerated" : true,
			"path" : "build/CMakeFiles/3.26.2/CMakeCXXCompiler.cmake"
		},
		{
			"isCMake" : true,
			"isExternal" : true,
			"path" : "/usr/local/share/cmake-3.26/Modules/CMakeSystemSpecificInformation.cmake"
		},
		{
			"isCMake" : true,
			"isExternal" : true,
			"path" : "/usr/local/share/cmake-3.26/Modules/CMakeGenericSystem.cmake"
		},
		{
			"isCMake" : true,
			"isExternal" : true,
			"path" : "/usr/local/share/cmake-3.26/Modules/CMakeInitializeConfigs.cmake"
		},
		{
			"isCMake" : true,
			"isExternal" : true,
			"path" : "/usr/local/share/cmake-3.26/Modules/Platform/Linux.cmake"
		},
		{
			"isCMake" : true,
			"isExternal" : true,
			"path" : "/usr/local/share/cmake-3.26/Modules/Platform/UnixPaths.cmake"
		},
		{
			"isCMake" : true,
			"isExternal" : true,
			"path" : "/usr/local/share/cmake-3.26/Modules/CMakeCInformation.cmake"
		},
		{
			"isCMake" : true,
			"isExternal" : true,
			"path" : "/usr/local/share/cmake-3.26/Modules/CMakeLanguageInformation.cmake"
		},
		{
			"isCMake" : true,
			"isExternal" : true,
			"path" : "/usr/local/share/cmake-3.26/Modules/Compiler/GNU-C.cmake"
		},
		{
			"isCMake" : true,
			"isExternal" : true,
			"path" : "/usr/local/share/cmake-3.26/Modules/Compiler/GNU.cmake"
		},
		{
			"isCMake" : true,
			"isExternal" : true,
			"path" : "/usr/local/share/cmake-3.26/Modules/Compiler/CMakeCommonCompilerMacros.cmake"
		},
		{
			"isCMake" : true,
			"isExternal" : true,
			"path" : "/usr/local/share/cmake-3.26/Modules/Platform/Linux-GNU-C.cmake"
		},
		{
			"isCMake" : true,
			"isExternal" : true,
			"path" : "/usr/local/share/cmake-3.26/Modules/Platform/Linux-GNU.cmake"
		},
		{
			"isCMake" : true,
			"isExternal" : true,
			"path" : "/usr/local/share/cmake-3.26/Modules/CMakeCommonLanguageInclude.cmake"
		},
		{
			"isCMake" : true,
			"isExternal" : true,
			"path" : "/usr/local/share/cmake-3.26/Modules/CMakeCXXInformation.cmake"
		},
		{
			"isCMake" : true,
			"isExternal" : true,
			"path" : "/usr/local/share/cmake-3.26/Modules/CMakeLanguageInformation.cmake"
		},
		{
			"isCMake" : true,
			"isExternal" : true,
			"path" : "/usr/local/share/cmake-3.26/Modules/Compiler/GNU-CXX.cmake"
		},
		{
			"isCMake" : true,
			"isExternal" : true,
			"path" : "/usr/local/share/cmake-3.26/Modules/Compiler/GNU.cmake"
		},
		{
			"isCMake" : true,
			"isExternal" : true,
			"path" : "/usr/local/share/cmake-3.26/Modules/Platform/Linux-GNU-CXX.cmake"
		},
		{
			"isCMake" : true,
			"isExternal" : true,
			"path" : "/usr/local/share/cmake-3.26/Modules/Platform/Linux-GNU.cmake"
		},
		{
			"isCMake" : true,
			"isExternal" : true,
			"path" : "/usr/local/share/cmake-3.26/Modules/CMakeCommonLanguageInclude.cmake"
		},
		{
			"isCMake" : true,
			"isExternal" : true,
			"path" : "/usr/local/share/cmake-3.26/Modules/FindBLAS.cmake"
		},
		{
			"isCMake" : true,
			"isExternal" : true,
			"path" : "/usr/local/share/cmake-3.26/Modules/CheckFunctionExists.cmake"
		},
		{
			"isCMake" : true,
			"isExternal" : true,
			"path" : "/usr/local/share/cmake-3.26/Modules/FindPackageHandleStandardArgs.cmake"
		},
		{
			"isCMake" : true,
			"isExternal" : true,
			"path" : "/usr/local/share/cmake-3.26/Modules/FindPackageMessage.cmake"
		},
		{
			"isCMake" : true,
			"isExternal" : true,
			"path" : "/usr/local/share/cmake-3.26/Modules/FindThreads.cmake"
		},
		{
			"isCMake" : true,
			"isExternal" : true,
			"path" : "/usr/local/share/cmake-3.26/Modules/CheckLibraryExists.cmake"
		},
		{
			"isCMake" : true,
			"isExternal" : true,
			"path" : "/usr/local/share/cmake-3.26/Modules/CheckIncludeFile.cmake"
		},
		{
			"isCMake" : true,
			"isExternal" : true,
			"path" : "/usr/local/share/cmake-3.26/Modules/CheckCSourceCompiles.cmake"
		},
		{
			"isCMake" : true,
			"isExternal" : true,
			"path" : "/usr/local/share/cmake-3.26/Modules/Internal/CheckSourceCompiles.cmake"
		},
		{
			"isCMake" : true,
			"isExternal" : true,
			"path" : "/usr/local/share/cmake-3.26/Modules/FindPackageHandleStandardArgs.cmake"
		},
		{
			"isCMake" : true,
			"isExternal" : true,
			"path" : "/usr/local/share/cmake-3.26/Modules/FindPackageMessage.cmake"
		},
		{
			"isExternal" : true,
			"path" : "/usr/lib/cmake/pybind11/pybind11ConfigVersion.cmake"
		},
		{
			"isExternal" : true,
			"path" : "/usr/lib/cmake/pybind11/pybind11Config.cmake"
		},
		{
			"isExternal" : true,
			"path" : "/usr/lib/cmake/pybind11/pybind11Targets.cmake"
		},
		{
			"isExternal" : true,
			"path" : "/usr/lib/cmake/pybind11/pybind11Common.cmake"
		},
		{
			"isExternal" : true,
			"path" : "/usr/lib/cmake/pybind11/pybind11Tools.cmake"
		},
		{
			"isCMake" : true,
			"isExternal" : true,
			"path" : "/usr/local/share/cmake-3.26/Modules/CMakeParseArguments.cmake"
		},
		{
			"isExternal" : true,
			"path" : "/usr/lib/cmake/pybind11/FindPythonLibsNew.cmake"
		},
		{
			"isCMake" : true,
			"isExternal" : true,
			"path" : "/usr/local/share/cmake-3.26/Modules/FindPythonInterp.cmake"
		},
		{
			"isCMake" : true,
			"isExternal" : true,
			"path" : "/usr/local/share/cmake-3.26/Modules/FindPackageHandleStandardArgs.cmake"
		},
		{
			"isCMake" : true,
			"isExternal" : true,
			"path" : "/usr/local/share/cmake-3.26/Modules/FindPackageMessage.cmake"
		},
		{
			"isCMake" : true,
			"isExternal" : true,
			"path" : "/usr/local/share/cmake-3.26/Modules/CheckCXXCompilerFlag.cmake"
		},
		{
			"isCMake" : true,
			"isExternal" : true,
			"path" : "/usr/local/share/cmake-3.26/Modules/CheckCXXSourceCompiles.cmake"
		},
		{
			"isCMake" : true,
			"isExternal" : true,
			"path" : "/usr/local/share/cmake-3.26/Modules/Internal/CheckSourceCompiles.cmake"
		},
		{
			"isCMake" : true,
			"isExternal" : true,
			"path" : "/usr/local/share/cmake-3.26/Modules/Internal/CheckCompilerFlag.cmake"
		},
		{
			"isCMake" : true,
			"isExternal" : true,
			"path" : "/usr/local/share/cmake-3.26/Modules/Internal/CheckFlagCommonConfig.cmake"
		},
		{
			"isCMake" : true,
			"isExternal" : true,
			"path" : "/usr/local/share/cmake-3.26/Modules/Internal/CheckSourceCompiles.cmake"
		},
		{
			"isCMake" : true,
			"isExternal" : true,
			"path" : "/usr/local/share/cmake-3.26/Modules/CMakeCheckCompilerFlagCommonPatterns.cmake"
		},
		{
			"isExternal" : true,
			"path" : "/usr/lib/x86_64-linux-gnu/cmake/opencv4/OpenCVConfig-version.cmake"
		},
		{
			"isExternal" : true,
			"path" : "/usr/lib/x86_64-linux-gnu/cmake/opencv4/OpenCVConfig.cmake"
		},
		{
			"isCMake" : true,
			"isExternal" : true,
			"path" : "/usr/local/share/cmake-3.26/Modules/FindPackageHandleStandardArgs.cmake"
		},
		{
			"isCMake" : true,
			"isExternal" : true,
			"path" : "/usr/local/share/cmake-3.26/Modules/FindPackageMessage.cmake"
		},
		{
			"isExternal" : true,
			"path" : "/usr/lib/x86_64-linux-gnu/cmake/opencv4/OpenCVModules.cmake"
		},
		{
			"isExternal" : true,
			"path" : "/usr/lib/x86_64-linux-gnu/cmake/opencv4/OpenCVModules-release.cmake"
		},
		{
			"isExternal" : true,
			"path" : "/usr/lib/x86_64-linux-gnu/cmake/dv/dv-config-version.cmake"
		},
		{
			"isExternal" : true,
			"path" : "/usr/lib/x86_64-linux-gnu/cmake/dv/dv-config.cmake"
		},
		{
			"isExternal" : true,
			"path" : "/usr/lib/x86_64-linux-gnu/cmake/dv-processing/dv-processing-config-version.cmake"
		},
		{
			"isExternal" : true,
			"path" : "/usr/lib/x86_64-linux-gnu/cmake/dv-processing/dv-processing-config.cmake"
		},
		{
			"isCMake" : true,
			"isExternal" : true,
			"path" : "/usr/local/share/cmake-3.26/Modules/FindBoost.cmake"
		},
		{
			"isCMake" : true,
			"isExternal" : true,
			"path" : "/usr/local/share/cmake-3.26/Modules/FindPackageHandleStandardArgs.cmake"
		},
		{
			"isCMake" : true,
			"isExternal" : true,
			"path" : "/usr/local/share/cmake-3.26/Modules/FindPackageMessage.cmake"
		},
		{
			"isCMake" : true,
			"isExternal" : true,
			"path" : "/usr/local/share/cmake-3.26/Modules/FindOpenSSL.cmake"
		},
		{
			"isCMake" : true,
			"isExternal" : true,
			"path" : "/usr/local/share/cmake-3.26/Modules/FindPkgConfig.cmake"
		},
		{
			"isCMake" : true,
			"isExternal" : true,
			"path" : "/usr/local/share/cmake-3.26/Modules/FindPackageHandleStandardArgs.cmake"
		},
		{
			"isCMake" : true,
			"isExternal" : true,
			"path" : "/usr/local/share/cmake-3.26/Modules/FindPackageMessage.cmake"
		},
		{
			"isCMake" : true,
			"isExternal" : true,
			"path" : "/usr/local/share/cmake-3.26/Modules/FindPackageHandleStandardArgs.cmake"
		},
		{
			"isCMake" : true,
			"isExternal" : true,
			"path" : "/usr/local/share/cmake-3.26/Modules/FindPackageMessage.cmake"
		},
		{
			"isExternal" : true,
			"path" : "/usr/share/eigen3/cmake/Eigen3ConfigVersion.cmake"
		},
		{
			"isExternal" : true,
			"path" : "/usr/share/eigen3/cmake/Eigen3Config.cmake"
		},
		{
			"isExternal" : true,
			"path" : "/usr/share/eigen3/cmake/Eigen3Targets.cmake"
		},
		{
			"isExternal" : true,
			"path" : "/usr/lib/x86_64-linux-gnu/cmake/opencv4/OpenCVConfig-version.cmake"
		},
		{
			"isExternal" : true,
			"path" : "/usr/lib/x86_64-linux-gnu/cmake/opencv4/OpenCVConfig.cmake"
		},
		{
			"isCMake" : true,
			"isExternal" : true,
			"path" : "/usr/local/share/cmake-3.26/Modules/FindPackageHandleStandardArgs.cmake"
		},
		{
			"isCMake" : true,
			"isExternal" : true,
			"path" : "/usr/local/share/cmake-3.26/Modules/FindPackageMessage.cmake"
		},
		{
			"isExternal" : true,
			"path" : "/usr/lib/x86_64-linux-gnu/cmake/fmt/fmt-config-version.cmake"
		},
		{
			"isExternal" : true,
			"path" : "/usr/lib/x86_64-linux-gnu/cmake/fmt/fmt-config.cmake"
		},
		{
			"isExternal" : true,
			"path" : "/usr/lib/x86_64-linux-gnu/cmake/fmt/fmt-targets.cmake"
		},
		{
			"isExternal" : true,
			"path" : "/usr/lib/x86_64-linux-gnu/cmake/fmt/fmt-targets-release.cmake"
		},
		{
			"isExternal" : true,
			"path" : "/usr/lib/x86_64-linux-gnu/cmake/libcaer/libcaerConfigVersion.cmake"
		},
		{
			"isExternal" : true,
			"path" : "/usr/lib/x86_64-linux-gnu/cmake/libcaer/libcaerConfig.cmake"
		},
		{
			"isExternal" : true,
			"path" : "/usr/lib/x86_64-linux-gnu/cmake/libcaer/libcaer-exports.cmake"
		},
		{
			"isExternal" : true,
			"path" : "/usr/lib/x86_64-linux-gnu/cmake/libcaer/libcaer-exports-release.cmake"
		},
		{
			"isCMake" : true,
			"isExternal" : true,
			"path" : "/usr/local/share/cmake-3.26/Modules/FindPkgConfig.cmake"
		},
		{
			"isCMake" : true,
			"isExternal" : true,
			"path" : "/usr/local/share/cmake-3.26/Modules/FindPackageHandleStandardArgs.cmake"
		},
		{
			"isCMake" : true,
			"isExternal" : true,
			"path" : "/usr/local/share/cmake-3.26/Modules/FindPackageMessage.cmake"
		},
		{
			"isCMake" : true,
			"isExternal" : true,
			"path" : "/usr/local/share/cmake-3.26/Modules/FindPkgConfig.cmake"
		},
		{
			"isCMake" : true,
			"isExternal" : true,
			"path" : "/usr/local/share/cmake-3.26/Modules/FindPackageHandleStandardArgs.cmake"
		},
		{
			"isCMake" : true,
			"isExternal" : true,
			"path" : "/usr/local/share/cmake-3.26/Modules/FindPackageMessage.cmake"
		},
		{
			"isExternal" : true,
			"path" : "/usr/lib/x86_64-linux-gnu/cmake/dv-processing/dv-processing-targets.cmake"
		},
		{
			"isExternal" : true,
			"path" : "/usr/lib/x86_64-linux-gnu/cmake/dv-processing/inivation-setup.cmake"
		},
		{
			"isCMake" : true,
			"isExternal" : true,
			"path" : "/usr/local/share/cmake-3.26/Modules/GNUInstallDirs.cmake"
		},
		{
			"isCMake" : true,
			"isExternal" : true,
			"path" : "/usr/local/share/cmake-3.26/Modules/TestBigEndian.cmake"
		},
		{
			"isCMake" : true,
			"isExternal" : true,
			"path" : "/usr/local/share/cmake-3.26/Modules/CheckTypeSize.cmake"
		},
		{
			"isCMake" : true,
			"isExternal" : true,
			"path" : "/usr/local/share/cmake-3.26/Modules/CheckIncludeFile.cmake"
		},
		{
			"isCMake" : true,
			"isExternal" : true,
			"path" : "/usr/local/share/cmake-3.26/Modules/CheckIncludeFileCXX.cmake"
		},
		{
			"isCMake" : true,
			"isExternal" : true,
			"path" : "/usr/local/share/cmake-3.26/Modules/CheckTypeSize.cmake"
		},
		{
			"isCMake" : true,
			"isExternal" : true,
			"path" : "/usr/local/share/cmake-3.26/Modules/CheckIncludeFile.cmake"
		},
		{
			"isCMake" : true,
			"isExternal" : true,
			"path" : "/usr/local/share/cmake-3.26/Modules/CheckIncludeFileCXX.cmake"
		},
		{
			"isCMake" : true,
			"isExternal" : true,
			"path" : "/usr/local/share/cmake-3.26/Modules/FindThreads.cmake"
		},
		{
			"isCMake" : true,
			"isExternal" : true,
			"path" : "/usr/local/share/cmake-3.26/Modules/CheckLibraryExists.cmake"
		},
		{
			"isCMake" : true,
			"isExternal" : true,
			"path" : "/usr/local/share/cmake-3.26/Modules/CheckIncludeFile.cmake"
		},
		{
			"isCMake" : true,
			"isExternal" : true,
			"path" : "/usr/local/share/cmake-3.26/Modules/CheckCSourceCompiles.cmake"
		},
		{
			"isCMake" : true,
			"isExternal" : true,
			"path" : "/usr/local/share/cmake-3.26/Modules/FindPackageHandleStandardArgs.cmake"
		},
		{
			"isCMake" : true,
			"isExternal" : true,
			"path" : "/usr/local/share/cmake-3.26/Modules/FindPackageMessage.cmake"
		},
		{
			"isCMake" : true,
			"isExternal" : true,
			"path" : "/usr/local/share/cmake-3.26/Modules/FindBoost.cmake"
		},
		{
			"isCMake" : true,
			"isExternal" : true,
			"path" : "/usr/local/share/cmake-3.26/Modules/FindPackageHandleStandardArgs.cmake"
		},
		{
			"isCMake" : true,
			"isExternal" : true,
			"path" : "/usr/local/share/cmake-3.26/Modules/FindPackageMessage.cmake"
		},
		{
			"isExternal" : true,
			"path" : "/usr/lib/x86_64-linux-gnu/cmake/dv/dv-targets.cmake"
		},
		{
			"isExternal" : true,
			"path" : "/usr/lib/x86_64-linux-gnu/cmake/dv/dv-targets-release.cmake"
		},
		{
			"isExternal" : true,
			"path" : "/home/kuga/Workspace/libtorch/share/cmake/Torch/TorchConfigVersion.cmake"
		},
		{
			"isExternal" : true,
			"path" : "/home/kuga/Workspace/libtorch/share/cmake/Torch/TorchConfig.cmake"
		},
		{
			"isCMake" : true,
			"isExternal" : true,
			"path" : "/usr/local/share/cmake-3.26/Modules/FindPackageHandleStandardArgs.cmake"
		},
		{
			"isCMake" : true,
			"isExternal" : true,
			"path" : "/usr/local/share/cmake-3.26/Modules/FindPackageMessage.cmake"
		},
		{
			"isExternal" : true,
			"path" : "/home/kuga/Workspace/libtorch/share/cmake/Caffe2/Caffe2ConfigVersion.cmake"
		},
		{
			"isExternal" : true,
			"path" : "/home/kuga/Workspace/libtorch/share/cmake/Caffe2/Caffe2Config.cmake"
		},
		{
			"isExternal" : true,
			"path" : "/home/kuga/Workspace/libtorch/share/cmake/Caffe2/public/utils.cmake"
		},
		{
			"isExternal" : true,
			"path" : "/home/kuga/Workspace/libtorch/share/cmake/Caffe2/public/cuda.cmake"
		},
		{
			"isExternal" : true,
			"path" : "/home/kuga/Workspace/libtorch/share/cmake/Caffe2/Modules_CUDA_fix/FindCUDA.cmake"
		},
		{
			"isExternal" : true,
			"path" : "/home/kuga/Workspace/libtorch/share/cmake/Caffe2/Modules_CUDA_fix/upstream/CMakeInitializeConfigs.cmake"
		},
		{
			"isExternal" : true,
			"path" : "/home/kuga/Workspace/libtorch/share/cmake/Caffe2/Modules_CUDA_fix/upstream/FindCUDA.cmake"
		},
		{
			"isExternal" : true,
			"path" : "/home/kuga/Workspace/libtorch/share/cmake/Caffe2/Modules_CUDA_fix/upstream/FindPackageHandleStandardArgs.cmake"
		},
		{
			"isExternal" : true,
			"path" : "/home/kuga/Workspace/libtorch/share/cmake/Caffe2/Modules_CUDA_fix/upstream/FindPackageMessage.cmake"
		},
		{
			"isExternal" : true,
			"path" : "/home/kuga/Workspace/libtorch/share/cmake/Caffe2/Modules_CUDA_fix/upstream/FindCUDA/select_compute_arch.cmake"
		},
		{
			"isGenerated" : true,
			"path" : "build/CMakeFiles/3.26.2/CMakeCUDACompiler.cmake"
		},
		{
			"isCMake" : true,
			"isExternal" : true,
			"path" : "/usr/local/share/cmake-3.26/Modules/CMakeCUDAInformation.cmake"
		},
		{
			"isCMake" : true,
			"isExternal" : true,
			"path" : "/usr/local/share/cmake-3.26/Modules/Compiler/NVIDIA-CUDA.cmake"
		},
		{
			"isCMake" : true,
			"isExternal" : true,
			"path" : "/usr/local/share/cmake-3.26/Modules/Compiler/CMakeCommonCompilerMacros.cmake"
		},
		{
			"isCMake" : true,
			"isExternal" : true,
			"path" : "/usr/local/share/cmake-3.26/Modules/CMakeCommonLanguageInclude.cmake"
		},
		{
			"isGenerated" : true,
			"path" : "build/detect_cuda_version.cc"
		},
		{
			"isGenerated" : true,
			"path" : "build/detect_cuda_compute_capabilities.cu"
		},
		{
			"isExternal" : true,
			"path" : "/home/kuga/Workspace/libtorch/share/cmake/Caffe2/public/mkl.cmake"
		},
		{
			"isExternal" : true,
			"path" : "/home/kuga/Workspace/libtorch/share/cmake/Caffe2/public/mkldnn.cmake"
		},
		{
			"isExternal" : true,
			"path" : "/home/kuga/Workspace/libtorch/share/cmake/Caffe2/Caffe2Targets.cmake"
		},
		{
			"isExternal" : true,
			"path" : "/home/kuga/Workspace/libtorch/share/cmake/Caffe2/Caffe2Targets-release.cmake"
		},
		{
			"path" : "include/CMakeLists.txt"
		},
		{
			"path" : "src/CMakeLists.txt"
		},
		{
			"path" : "src/_denoisor/CMakeLists.txt"
		},
		{
			"path" : "src/_denoisor/reclusive_event_denoisor/CMakeLists.txt"
		},
		{
			"path" : "src/_denoisor/yang_noise/CMakeLists.txt"
		},
		{
			"path" : "src/_denoisor/double_window_filter/CMakeLists.txt"
		},
		{
			"path" : "src/_denoisor/khodamoradi_noise/CMakeLists.txt"
		},
		{
			"path" : "src/_denoisor/time_surface/CMakeLists.txt"
		},
		{
			"path" : "src/_denoisor/multiLayer_perceptron_filter/CMakeLists.txt"
		}
	],
	"kind" : "cmakeFiles",
	"paths" : 
	{
		"build" : "/home/kuga/Workspace/tmp-emlb-v2/build",
		"source" : "/home/kuga/Workspace/tmp-emlb-v2"
	},
	"version" : 
	{
		"major" : 1,
		"minor" : 0
	}
}
